clockify_seon_client/__init__.py
clockify_seon_client/factory/__init__.py
clockify_seon_client/factory/factory.py
clockify_seon_client/factory/service_enum.py
clockify_seon_client/service/__init__.py
clockify_seon_client/service/clockify_service.py
clockify_seon_client-2.0.1.dist-info/METADATA
clockify_seon_client-2.0.1.dist-info/WHEEL
clockify_seon_client-2.0.1.dist-info/top_level.txt
clockify_seon_client-2.0.1.dist-info/RECORD
