Metadata-Version: 2.1
Name: clockify-seon-client
Version: 2.0.1
Summary: Responsible for integration clockify and seon
Home-page: https://github.com/paulossjunior/tfs_integration_seon
Author: Paulo Sergio dos Santo Junior
Author-email: paulossjuniort@gmail.com
License: UNKNOWN
Platform: UNKNOWN
Classifier: Programming Language :: Python :: 3
Classifier: License :: OSI Approved :: MIT License
Classifier: Operating System :: OS Independent
Requires-Dist: rabbitmqX
